krtek/__init__.py
krtek/coefficients.py
krtek/computation.py
krtek/logic.py
krtek/quantifiers.py
krtek/utils.py
krtek/guha/__init__.py
krtek/guha/cedents.py
krtek/guha/four_ft_miner.py
krtek/guha/generation.py
krtek/redescription/__init__.py
krtek/redescription/reremi.py
krtek/redescription/trie.py
krtek-1.0.0.dist-info/licenses/LICENCE
krtek-1.0.0.dist-info/METADATA
krtek-1.0.0.dist-info/WHEEL
krtek-1.0.0.dist-info/top_level.txt
krtek-1.0.0.dist-info/RECORD
