Metadata-Version: 2.4
Name: krtek
Version: 1.0.0
Summary: Package for mining association rules using GUHA and Redescription mining.
Home-page: https://github.com/slunimara
Author: Marek Brodacký
Author-email: brodackym@gmail.com
License: MIT
Keywords: GUHA,Redescription mining,Association rules,Data mining
Classifier: Programming Language :: Python :: 3.11
Classifier: Intended Audience :: Science/Research
Classifier: Natural Language :: English
Classifier: Typing :: Typed
License-File: LICENCE
Requires-Dist: numpy
Requires-Dist: pandas
Dynamic: author
Dynamic: author-email
Dynamic: classifier
Dynamic: description
Dynamic: description-content-type
Dynamic: home-page
Dynamic: keywords
Dynamic: license
Dynamic: license-file
Dynamic: requires-dist
Dynamic: summary
